{"vertices":[{"@id":1,"shape":{"type":"rectangle","xposition":"NaN","yposition":"NaN","width":"NaN","height":"NaN","color":{"argb":"ff000000"}},"labelManager":{"labels":[{"type":"text","@id":2,"inputText":"006cbef51dfa5c44","font":{"fontName":"SansSerif.plain","style":0,"size":10},"noBreak":false,"color":{"argb":"ff000000"},"placement":"FREE","horizontalPlacement":"FREE","verticalPlacement":"FREE","showLabel":true,"shape":null,"layoutText":null}],"mainLabel":2},"portCompositions":[{"type":"portGroup","@id":3,"ordered":false,"portCompositions":[{"type":"port","@id":4,"shape":{"type":"rectangle","xposition":"NaN","yposition":"NaN","width":"NaN","height":"NaN","color":{"argb":"ff000000"}},"labelManager":{"labels":[{"type":"text","@id":5,"inputText":"A.1","font":{"fontName":"SansSerif.plain","style":0,"size":10},"noBreak":false,"color":{"argb":"ff000000"},"placement":"FREE","horizontalPlacement":"FREE","verticalPlacement":"FREE","showLabel":true,"shape":null,"layoutText":null}],"mainLabel":5},"orientationAtVertex":"FREE","reference":null},{"type":"port","@id":6,"shape":{"type":"rectangle","xposition":"NaN","yposition":"NaN","width":"NaN","height":"NaN","color":{"argb":"ff000000"}},"labelManager":{"labels":[{"type":"text","@id":7,"inputText":"A.2","font":{"fontName":"SansSerif.plain","style":0,"size":10},"noBreak":false,"color":{"argb":"ff000000"},"placement":"FREE","horizontalPlacement":"FREE","verticalPlacement":"FREE","showLabel":true,"shape":null,"layoutText":null}],"mainLabel":7},"orientationAtVertex":"FREE","reference":null}],"reference":null}],"reference":null},{"@id":8,"shape":{"type":"rectangle","xposition":"NaN","yposition":"NaN","width":"NaN","height":"NaN","color":{"argb":"ff000000"}},"labelManager":{"labels":[{"type":"text","@id":9,"inputText":"7d1cfa343d615293","font":{"fontName":"SansSerif.plain","style":0,"size":10},"noBreak":false,"color":{"argb":"ff000000"},"placement":"FREE","horizontalPlacement":"FREE","verticalPlacement":"FREE","showLabel":true,"shape":null,"layoutText":null}],"mainLabel":9},"portCompositions":[{"type":"portGroup","@id":10,"ordered":false,"portCompositions":[{"type":"port","@id":11,"shape":{"type":"rectangle","xposition":"NaN","yposition":"NaN","width":"NaN","height":"NaN","color":{"argb":"ff000000"}},"labelManager":{"labels":[{"type":"text","@id":12,"inputText":"B.1","font":{"fontName":"SansSerif.plain","style":0,"size":10},"noBreak":false,"color":{"argb":"ff000000"},"placement":"FREE","horizontalPlacement":"FREE","verticalPlacement":"FREE","showLabel":true,"shape":null,"layoutText":null}],"mainLabel":12},"orientationAtVertex":"FREE","reference":null},{"type":"port","@id":13,"shape":{"type":"rectangle","xposition":"NaN","yposition":"NaN","width":"NaN","height":"NaN","color":{"argb":"ff000000"}},"labelManager":{"labels":[{"type":"text","@id":14,"inputText":"B.2","font":{"fontName":"SansSerif.plain","style":0,"size":10},"noBreak":false,"color":{"argb":"ff000000"},"placement":"FREE","horizontalPlacement":"FREE","verticalPlacement":"FREE","showLabel":true,"shape":null,"layoutText":null}],"mainLabel":14},"orientationAtVertex":"FREE","reference":null}],"reference":null}],"reference":null},{"@id":15,"shape":{"type":"rectangle","xposition":"NaN","yposition":"NaN","width":"NaN","height":"NaN","color":{"argb":"ff000000"}},"labelManager":{"labels":[{"type":"text","@id":16,"inputText":"5696f314bfa62128","font":{"fontName":"SansSerif.plain","style":0,"size":10},"noBreak":false,"color":{"argb":"ff000000"},"placement":"FREE","horizontalPlacement":"FREE","verticalPlacement":"FREE","showLabel":true,"shape":null,"layoutText":null}],"mainLabel":16},"portCompositions":[{"type":"portGroup","@id":17,"ordered":false,"portCompositions":[{"type":"port","@id":18,"shape":{"type":"rectangle","xposition":"NaN","yposition":"NaN","width":"NaN","height":"NaN","color":{"argb":"ff000000"}},"labelManager":{"labels":[{"type":"text","@id":19,"inputText":"A.1","font":{"fontName":"SansSerif.plain","style":0,"size":10},"noBreak":false,"color":{"argb":"ff000000"},"placement":"FREE","horizontalPlacement":"FREE","verticalPlacement":"FREE","showLabel":true,"shape":null,"layoutText":null}],"mainLabel":19},"orientationAtVertex":"FREE","reference":null},{"type":"port","@id":20,"shape":{"type":"rectangle","xposition":"NaN","yposition":"NaN","width":"NaN","height":"NaN","color":{"argb":"ff000000"}},"labelManager":{"labels":[{"type":"text","@id":21,"inputText":"A.2","font":{"fontName":"SansSerif.plain","style":0,"size":10},"noBreak":false,"color":{"argb":"ff000000"},"placement":"FREE","horizontalPlacement":"FREE","verticalPlacement":"FREE","showLabel":true,"shape":null,"layoutText":null}],"mainLabel":21},"orientationAtVertex":"FREE","reference":null}],"reference":null}],"reference":null},{"@id":22,"shape":{"type":"rectangle","xposition":"NaN","yposition":"NaN","width":"NaN","height":"NaN","color":{"argb":"ff000000"}},"labelManager":{"labels":[{"type":"text","@id":23,"inputText":"b20385a0c829ef7f","font":{"fontName":"SansSerif.plain","style":0,"size":10},"noBreak":false,"color":{"argb":"ff000000"},"placement":"FREE","horizontalPlacement":"FREE","verticalPlacement":"FREE","showLabel":true,"shape":null,"layoutText":null}],"mainLabel":23},"portCompositions":[{"type":"portGroup","@id":24,"ordered":false,"portCompositions":[{"type":"port","@id":25,"shape":{"type":"rectangle","xposition":"NaN","yposition":"NaN","width":"NaN","height":"NaN","color":{"argb":"ff000000"}},"labelManager":{"labels":[{"type":"text","@id":26,"inputText":"B.1","font":{"fontName":"SansSerif.plain","style":0,"size":10},"noBreak":false,"color":{"argb":"ff000000"},"placement":"FREE","horizontalPlacement":"FREE","verticalPlacement":"FREE","showLabel":true,"shape":null,"layoutText":null}],"mainLabel":26},"orientationAtVertex":"FREE","reference":null},{"type":"port","@id":27,"shape":{"type":"rectangle","xposition":"NaN","yposition":"NaN","width":"NaN","height":"NaN","color":{"argb":"ff000000"}},"labelManager":{"labels":[{"type":"text","@id":28,"inputText":"B.2","font":{"fontName":"SansSerif.plain","style":0,"size":10},"noBreak":false,"color":{"argb":"ff000000"},"placement":"FREE","horizontalPlacement":"FREE","verticalPlacement":"FREE","showLabel":true,"shape":null,"layoutText":null}],"mainLabel":28},"orientationAtVertex":"FREE","reference":null}],"reference":null}],"reference":null},{"@id":29,"shape":{"type":"rectangle","xposition":"NaN","yposition":"NaN","width":"NaN","height":"NaN","color":{"argb":"ff000000"}},"labelManager":{"labels":[{"type":"text","@id":30,"inputText":"791fcbd2b89fbf4a","font":{"fontName":"SansSerif.plain","style":0,"size":10},"noBreak":false,"color":{"argb":"ff000000"},"placement":"FREE","horizontalPlacement":"FREE","verticalPlacement":"FREE","showLabel":true,"shape":null,"layoutText":null}],"mainLabel":30},"portCompositions":[{"type":"portGroup","@id":31,"ordered":false,"portCompositions":[{"type":"port","@id":32,"shape":{"type":"rectangle","xposition":"NaN","yposition":"NaN","width":"NaN","height":"NaN","color":{"argb":"ff000000"}},"labelManager":{"labels":[{"type":"text","@id":33,"inputText":"A.1","font":{"fontName":"SansSerif.plain","style":0,"size":10},"noBreak":false,"color":{"argb":"ff000000"},"placement":"FREE","horizontalPlacement":"FREE","verticalPlacement":"FREE","showLabel":true,"shape":null,"layoutText":null}],"mainLabel":33},"orientationAtVertex":"FREE","reference":null}],"reference":null}],"reference":null},{"@id":34,"shape":{"type":"rectangle","xposition":"NaN","yposition":"NaN","width":"NaN","height":"NaN","color":{"argb":"ff000000"}},"labelManager":{"labels":[{"type":"text","@id":35,"inputText":"9aed97458f067a5b","font":{"fontName":"SansSerif.plain","style":0,"size":10},"noBreak":false,"color":{"argb":"ff000000"},"placement":"FREE","horizontalPlacement":"FREE","verticalPlacement":"FREE","showLabel":true,"shape":null,"layoutText":null}],"mainLabel":35},"portCompositions":[{"type":"portGroup","@id":36,"ordered":false,"portCompositions":[{"type":"port","@id":37,"shape":{"type":"rectangle","xposition":"NaN","yposition":"NaN","width":"NaN","height":"NaN","color":{"argb":"ff000000"}},"labelManager":{"labels":[{"type":"text","@id":38,"inputText":"B.1","font":{"fontName":"SansSerif.plain","style":0,"size":10},"noBreak":false,"color":{"argb":"ff000000"},"placement":"FREE","horizontalPlacement":"FREE","verticalPlacement":"FREE","showLabel":true,"shape":null,"layoutText":null}],"mainLabel":38},"orientationAtVertex":"FREE","reference":null}],"reference":null}],"reference":null},{"@id":39,"shape":{"type":"rectangle","xposition":"NaN","yposition":"NaN","width":"NaN","height":"NaN","color":{"argb":"ff000000"}},"labelManager":{"labels":[{"type":"text","@id":40,"inputText":"76d1ade9008ed105","font":{"fontName":"SansSerif.plain","style":0,"size":10},"noBreak":false,"color":{"argb":"ff000000"},"placement":"FREE","horizontalPlacement":"FREE","verticalPlacement":"FREE","showLabel":true,"shape":null,"layoutText":null}],"mainLabel":40},"portCompositions":[{"type":"portGroup","@id":41,"ordered":false,"portCompositions":[{"type":"port","@id":42,"shape":{"type":"rectangle","xposition":"NaN","yposition":"NaN","width":"NaN","height":"NaN","color":{"argb":"ff000000"}},"labelManager":{"labels":[{"type":"text","@id":43,"inputText":"A.1","font":{"fontName":"SansSerif.plain","style":0,"size":10},"noBreak":false,"color":{"argb":"ff000000"},"placement":"FREE","horizontalPlacement":"FREE","verticalPlacement":"FREE","showLabel":true,"shape":null,"layoutText":null}],"mainLabel":43},"orientationAtVertex":"FREE","reference":null}],"reference":null}],"reference":null},{"@id":44,"shape":{"type":"rectangle","xposition":"NaN","yposition":"NaN","width":"NaN","height":"NaN","color":{"argb":"ff000000"}},"labelManager":{"labels":[{"type":"text","@id":45,"inputText":"82c0a8f6fa3dd874","font":{"fontName":"SansSerif.plain","style":0,"size":10},"noBreak":false,"color":{"argb":"ff000000"},"placement":"FREE","horizontalPlacement":"FREE","verticalPlacement":"FREE","showLabel":true,"shape":null,"layoutText":null}],"mainLabel":45},"portCompositions":[{"type":"portGroup","@id":46,"ordered":false,"portCompositions":[{"type":"port","@id":47,"shape":{"type":"rectangle","xposition":"NaN","yposition":"NaN","width":"NaN","height":"NaN","color":{"argb":"ff000000"}},"labelManager":{"labels":[{"type":"text","@id":48,"inputText":"B.1","font":{"fontName":"SansSerif.plain","style":0,"size":10},"noBreak":false,"color":{"argb":"ff000000"},"placement":"FREE","horizontalPlacement":"FREE","verticalPlacement":"FREE","showLabel":true,"shape":null,"layoutText":null}],"mainLabel":48},"orientationAtVertex":"FREE","reference":null}],"reference":null}],"reference":null},{"@id":49,"shape":{"type":"rectangle","xposition":"NaN","yposition":"NaN","width":"NaN","height":"NaN","color":{"argb":"ff000000"}},"labelManager":{"labels":[{"type":"text","@id":50,"inputText":"3753309cc6b7ac70","font":{"fontName":"SansSerif.plain","style":0,"size":10},"noBreak":false,"color":{"argb":"ff000000"},"placement":"FREE","horizontalPlacement":"FREE","verticalPlacement":"FREE","showLabel":true,"shape":null,"layoutText":null}],"mainLabel":50},"portCompositions":[{"type":"portGroup","@id":51,"ordered":false,"portCompositions":[{"type":"port","@id":52,"shape":{"type":"rectangle","xposition":"NaN","yposition":"NaN","width":"NaN","height":"NaN","color":{"argb":"ff000000"}},"labelManager":{"labels":[{"type":"text","@id":53,"inputText":"A.1","font":{"fontName":"SansSerif.plain","style":0,"size":10},"noBreak":false,"color":{"argb":"ff000000"},"placement":"FREE","horizontalPlacement":"FREE","verticalPlacement":"FREE","showLabel":true,"shape":null,"layoutText":null}],"mainLabel":53},"orientationAtVertex":"FREE","reference":null},{"type":"port","@id":54,"shape":{"type":"rectangle","xposition":"NaN","yposition":"NaN","width":"NaN","height":"NaN","color":{"argb":"ff000000"}},"labelManager":{"labels":[{"type":"text","@id":55,"inputText":"A.3","font":{"fontName":"SansSerif.plain","style":0,"size":10},"noBreak":false,"color":{"argb":"ff000000"},"placement":"FREE","horizontalPlacement":"FREE","verticalPlacement":"FREE","showLabel":true,"shape":null,"layoutText":null}],"mainLabel":55},"orientationAtVertex":"FREE","reference":null},{"type":"port","@id":56,"shape":{"type":"rectangle","xposition":"NaN","yposition":"NaN","width":"NaN","height":"NaN","color":{"argb":"ff000000"}},"labelManager":{"labels":[{"type":"text","@id":57,"inputText":"A.5","font":{"fontName":"SansSerif.plain","style":0,"size":10},"noBreak":false,"color":{"argb":"ff000000"},"placement":"FREE","horizontalPlacement":"FREE","verticalPlacement":"FREE","showLabel":true,"shape":null,"layoutText":null}],"mainLabel":57},"orientationAtVertex":"FREE","reference":null},{"type":"port","@id":58,"shape":{"type":"rectangle","xposition":"NaN","yposition":"NaN","width":"NaN","height":"NaN","color":{"argb":"ff000000"}},"labelManager":{"labels":[{"type":"text","@id":59,"inputText":"A.4","font":{"fontName":"SansSerif.plain","style":0,"size":10},"noBreak":false,"color":{"argb":"ff000000"},"placement":"FREE","horizontalPlacement":"FREE","verticalPlacement":"FREE","showLabel":true,"shape":null,"layoutText":null}],"mainLabel":59},"orientationAtVertex":"FREE","reference":null},{"type":"port","@id":60,"shape":{"type":"rectangle","xposition":"NaN","yposition":"NaN","width":"NaN","height":"NaN","color":{"argb":"ff000000"}},"labelManager":{"labels":[{"type":"text","@id":61,"inputText":"A.2","font":{"fontName":"SansSerif.plain","style":0,"size":10},"noBreak":false,"color":{"argb":"ff000000"},"placement":"FREE","horizontalPlacement":"FREE","verticalPlacement":"FREE","showLabel":true,"shape":null,"layoutText":null}],"mainLabel":61},"orientationAtVertex":"FREE","reference":null}],"reference":null}],"reference":null},{"@id":62,"shape":{"type":"rectangle","xposition":"NaN","yposition":"NaN","width":"NaN","height":"NaN","color":{"argb":"ff000000"}},"labelManager":{"labels":[{"type":"text","@id":63,"inputText":"3d8b4bf0b5b19421","font":{"fontName":"SansSerif.plain","style":0,"size":10},"noBreak":false,"color":{"argb":"ff000000"},"placement":"FREE","horizontalPlacement":"FREE","verticalPlacement":"FREE","showLabel":true,"shape":null,"layoutText":null}],"mainLabel":63},"portCompositions":[{"type":"portGroup","@id":64,"ordered":false,"portCompositions":[{"type":"port","@id":65,"shape":{"type":"rectangle","xposition":"NaN","yposition":"NaN","width":"NaN","height":"NaN","color":{"argb":"ff000000"}},"labelManager":{"labels":[{"type":"text","@id":66,"inputText":"B.1","font":{"fontName":"SansSerif.plain","style":0,"size":10},"noBreak":false,"color":{"argb":"ff000000"},"placement":"FREE","horizontalPlacement":"FREE","verticalPlacement":"FREE","showLabel":true,"shape":null,"layoutText":null}],"mainLabel":66},"orientationAtVertex":"FREE","reference":null},{"type":"port","@id":67,"shape":{"type":"rectangle","xposition":"NaN","yposition":"NaN","width":"NaN","height":"NaN","color":{"argb":"ff000000"}},"labelManager":{"labels":[{"type":"text","@id":68,"inputText":"B.3","font":{"fontName":"SansSerif.plain","style":0,"size":10},"noBreak":false,"color":{"argb":"ff000000"},"placement":"FREE","horizontalPlacement":"FREE","verticalPlacement":"FREE","showLabel":true,"shape":null,"layoutText":null}],"mainLabel":68},"orientationAtVertex":"FREE","reference":null},{"type":"port","@id":69,"shape":{"type":"rectangle","xposition":"NaN","yposition":"NaN","width":"NaN","height":"NaN","color":{"argb":"ff000000"}},"labelManager":{"labels":[{"type":"text","@id":70,"inputText":"B.5","font":{"fontName":"SansSerif.plain","style":0,"size":10},"noBreak":false,"color":{"argb":"ff000000"},"placement":"FREE","horizontalPlacement":"FREE","verticalPlacement":"FREE","showLabel":true,"shape":null,"layoutText":null}],"mainLabel":70},"orientationAtVertex":"FREE","reference":null},{"type":"port","@id":71,"shape":{"type":"rectangle","xposition":"NaN","yposition":"NaN","width":"NaN","height":"NaN","color":{"argb":"ff000000"}},"labelManager":{"labels":[{"type":"text","@id":72,"inputText":"B.4","font":{"fontName":"SansSerif.plain","style":0,"size":10},"noBreak":false,"color":{"argb":"ff000000"},"placement":"FREE","horizontalPlacement":"FREE","verticalPlacement":"FREE","showLabel":true,"shape":null,"layoutText":null}],"mainLabel":72},"orientationAtVertex":"FREE","reference":null},{"type":"port","@id":73,"shape":{"type":"rectangle","xposition":"NaN","yposition":"NaN","width":"NaN","height":"NaN","color":{"argb":"ff000000"}},"labelManager":{"labels":[{"type":"text","@id":74,"inputText":"B.2","font":{"fontName":"SansSerif.plain","style":0,"size":10},"noBreak":false,"color":{"argb":"ff000000"},"placement":"FREE","horizontalPlacement":"FREE","verticalPlacement":"FREE","showLabel":true,"shape":null,"layoutText":null}],"mainLabel":74},"orientationAtVertex":"FREE","reference":null}],"reference":null}],"reference":null},{"@id":75,"shape":{"type":"rectangle","xposition":"NaN","yposition":"NaN","width":"NaN","height":"NaN","color":{"argb":"ff000000"}},"labelManager":{"labels":[{"type":"text","@id":76,"inputText":"e9800998ecf8427e","font":{"fontName":"SansSerif.plain","style":0,"size":10},"noBreak":false,"color":{"argb":"ff000000"},"placement":"FREE","horizontalPlacement":"FREE","verticalPlacement":"FREE","showLabel":true,"shape":null,"layoutText":null}],"mainLabel":76},"portCompositions":[{"type":"port","@id":77,"shape":{"type":"rectangle","xposition":"NaN","yposition":"NaN","width":"NaN","height":"NaN","color":{"argb":"ff000000"}},"labelManager":{"labels":[{"type":"text","@id":78,"inputText":"","font":{"fontName":"SansSerif.plain","style":0,"size":10},"noBreak":false,"color":{"argb":"ff000000"},"placement":"FREE","horizontalPlacement":"FREE","verticalPlacement":"FREE","showLabel":true,"shape":null,"layoutText":null}],"mainLabel":78},"orientationAtVertex":"FREE","reference":null}],"reference":null},{"@id":79,"shape":{"type":"rectangle","xposition":"NaN","yposition":"NaN","width":"NaN","height":"NaN","color":{"argb":"ff000000"}},"labelManager":{"labels":[{"type":"text","@id":80,"inputText":"48c77b41e7d232c8","font":{"fontName":"SansSerif.plain","style":0,"size":10},"noBreak":false,"color":{"argb":"ff000000"},"placement":"FREE","horizontalPlacement":"FREE","verticalPlacement":"FREE","showLabel":true,"shape":null,"layoutText":null}],"mainLabel":80},"portCompositions":[{"type":"portGroup","@id":81,"ordered":false,"portCompositions":[{"type":"port","@id":82,"shape":{"type":"rectangle","xposition":"NaN","yposition":"NaN","width":"NaN","height":"NaN","color":{"argb":"ff000000"}},"labelManager":{"labels":[{"type":"text","@id":83,"inputText":"A.4","font":{"fontName":"SansSerif.plain","style":0,"size":10},"noBreak":false,"color":{"argb":"ff000000"},"placement":"FREE","horizontalPlacement":"FREE","verticalPlacement":"FREE","showLabel":true,"shape":null,"layoutText":null}],"mainLabel":83},"orientationAtVertex":"FREE","reference":null},{"type":"port","@id":84,"shape":{"type":"rectangle","xposition":"NaN","yposition":"NaN","width":"NaN","height":"NaN","color":{"argb":"ff000000"}},"labelManager":{"labels":[{"type":"text","@id":85,"inputText":"A.1","font":{"fontName":"SansSerif.plain","style":0,"size":10},"noBreak":false,"color":{"argb":"ff000000"},"placement":"FREE","horizontalPlacement":"FREE","verticalPlacement":"FREE","showLabel":true,"shape":null,"layoutText":null}],"mainLabel":85},"orientationAtVertex":"FREE","reference":null},{"type":"port","@id":86,"shape":{"type":"rectangle","xposition":"NaN","yposition":"NaN","width":"NaN","height":"NaN","color":{"argb":"ff000000"}},"labelManager":{"labels":[{"type":"text","@id":87,"inputText":"A.3","font":{"fontName":"SansSerif.plain","style":0,"size":10},"noBreak":false,"color":{"argb":"ff000000"},"placement":"FREE","horizontalPlacement":"FREE","verticalPlacement":"FREE","showLabel":true,"shape":null,"layoutText":null}],"mainLabel":87},"orientationAtVertex":"FREE","reference":null},{"type":"port","@id":88,"shape":{"type":"rectangle","xposition":"NaN","yposition":"NaN","width":"NaN","height":"NaN","color":{"argb":"ff000000"}},"labelManager":{"labels":[{"type":"text","@id":89,"inputText":"A.2","font":{"fontName":"SansSerif.plain","style":0,"size":10},"noBreak":false,"color":{"argb":"ff000000"},"placement":"FREE","horizontalPlacement":"FREE","verticalPlacement":"FREE","showLabel":true,"shape":null,"layoutText":null}],"mainLabel":89},"orientationAtVertex":"FREE","reference":null}],"reference":null}],"reference":null},{"@id":90,"shape":{"type":"rectangle","xposition":"NaN","yposition":"NaN","width":"NaN","height":"NaN","color":{"argb":"ff000000"}},"labelManager":{"labels":[{"type":"text","@id":91,"inputText":"e550c225820fc9af","font":{"fontName":"SansSerif.plain","style":0,"size":10},"noBreak":false,"color":{"argb":"ff000000"},"placement":"FREE","horizontalPlacement":"FREE","verticalPlacement":"FREE","showLabel":true,"shape":null,"layoutText":null}],"mainLabel":91},"portCompositions":[{"type":"portGroup","@id":92,"ordered":false,"portCompositions":[{"type":"port","@id":93,"shape":{"type":"rectangle","xposition":"NaN","yposition":"NaN","width":"NaN","height":"NaN","color":{"argb":"ff000000"}},"labelManager":{"labels":[{"type":"text","@id":94,"inputText":"B.4","font":{"fontName":"SansSerif.plain","style":0,"size":10},"noBreak":false,"color":{"argb":"ff000000"},"placement":"FREE","horizontalPlacement":"FREE","verticalPlacement":"FREE","showLabel":true,"shape":null,"layoutText":null}],"mainLabel":94},"orientationAtVertex":"FREE","reference":null},{"type":"port","@id":95,"shape":{"type":"rectangle","xposition":"NaN","yposition":"NaN","width":"NaN","height":"NaN","color":{"argb":"ff000000"}},"labelManager":{"labels":[{"type":"text","@id":96,"inputText":"B.1","font":{"fontName":"SansSerif.plain","style":0,"size":10},"noBreak":false,"color":{"argb":"ff000000"},"placement":"FREE","horizontalPlacement":"FREE","verticalPlacement":"FREE","showLabel":true,"shape":null,"layoutText":null}],"mainLabel":96},"orientationAtVertex":"FREE","reference":null},{"type":"port","@id":97,"shape":{"type":"rectangle","xposition":"NaN","yposition":"NaN","width":"NaN","height":"NaN","color":{"argb":"ff000000"}},"labelManager":{"labels":[{"type":"text","@id":98,"inputText":"B.3","font":{"fontName":"SansSerif.plain","style":0,"size":10},"noBreak":false,"color":{"argb":"ff000000"},"placement":"FREE","horizontalPlacement":"FREE","verticalPlacement":"FREE","showLabel":true,"shape":null,"layoutText":null}],"mainLabel":98},"orientationAtVertex":"FREE","reference":null},{"type":"port","@id":99,"shape":{"type":"rectangle","xposition":"NaN","yposition":"NaN","width":"NaN","height":"NaN","color":{"argb":"ff000000"}},"labelManager":{"labels":[{"type":"text","@id":100,"inputText":"B.2","font":{"fontName":"SansSerif.plain","style":0,"size":10},"noBreak":false,"color":{"argb":"ff000000"},"placement":"FREE","horizontalPlacement":"FREE","verticalPlacement":"FREE","showLabel":true,"shape":null,"layoutText":null}],"mainLabel":100},"orientationAtVertex":"FREE","reference":null}],"reference":null}],"reference":null},{"@id":101,"shape":{"type":"rectangle","xposition":"NaN","yposition":"NaN","width":"NaN","height":"NaN","color":{"argb":"ff000000"}},"labelManager":{"labels":[{"type":"text","@id":102,"inputText":"207e5fa33acaaeea","font":{"fontName":"SansSerif.plain","style":0,"size":10},"noBreak":false,"color":{"argb":"ff000000"},"placement":"FREE","horizontalPlacement":"FREE","verticalPlacement":"FREE","showLabel":true,"shape":null,"layoutText":null}],"mainLabel":102},"portCompositions":[{"type":"portGroup","@id":103,"ordered":false,"portCompositions":[],"reference":null},{"type":"portGroup","@id":104,"ordered":false,"portCompositions":[{"type":"port","@id":105,"shape":{"type":"rectangle","xposition":"NaN","yposition":"NaN","width":"NaN","height":"NaN","color":{"argb":"ff000000"}},"labelManager":{"labels":[{"type":"text","@id":106,"inputText":"A.1","font":{"fontName":"SansSerif.plain","style":0,"size":10},"noBreak":false,"color":{"argb":"ff000000"},"placement":"FREE","horizontalPlacement":"FREE","verticalPlacement":"FREE","showLabel":true,"shape":null,"layoutText":null}],"mainLabel":106},"orientationAtVertex":"FREE","reference":null}],"reference":null}],"reference":null},{"@id":107,"shape":{"type":"rectangle","xposition":"NaN","yposition":"NaN","width":"NaN","height":"NaN","color":{"argb":"ff000000"}},"labelManager":{"labels":[{"type":"text","@id":108,"inputText":"8b64668f1c5b6e3a","font":{"fontName":"SansSerif.plain","style":0,"size":10},"noBreak":false,"color":{"argb":"ff000000"},"placement":"FREE","horizontalPlacement":"FREE","verticalPlacement":"FREE","showLabel":true,"shape":null,"layoutText":null}],"mainLabel":108},"portCompositions":[{"type":"portGroup","@id":109,"ordered":false,"portCompositions":[{"type":"port","@id":110,"shape":{"type":"rectangle","xposition":"NaN","yposition":"NaN","width":"NaN","height":"NaN","color":{"argb":"ff000000"}},"labelManager":{"labels":[{"type":"text","@id":111,"inputText":"B.1","font":{"fontName":"SansSerif.plain","style":0,"size":10},"noBreak":false,"color":{"argb":"ff000000"},"placement":"FREE","horizontalPlacement":"FREE","verticalPlacement":"FREE","showLabel":true,"shape":null,"layoutText":null}],"mainLabel":111},"orientationAtVertex":"FREE","reference":null}],"reference":null}],"reference":null},{"@id":112,"shape":{"type":"rectangle","xposition":"NaN","yposition":"NaN","width":"NaN","height":"NaN","color":{"argb":"ff000000"}},"labelManager":{"labels":[{"type":"text","@id":113,"inputText":"e9800998ecf8427e","font":{"fontName":"SansSerif.plain","style":0,"size":10},"noBreak":false,"color":{"argb":"ff000000"},"placement":"FREE","horizontalPlacement":"FREE","verticalPlacement":"FREE","showLabel":true,"shape":null,"layoutText":null}],"mainLabel":113},"portCompositions":[{"type":"port","@id":114,"shape":{"type":"rectangle","xposition":"NaN","yposition":"NaN","width":"NaN","height":"NaN","color":{"argb":"ff000000"}},"labelManager":{"labels":[{"type":"text","@id":115,"inputText":"","font":{"fontName":"SansSerif.plain","style":0,"size":10},"noBreak":false,"color":{"argb":"ff000000"},"placement":"FREE","horizontalPlacement":"FREE","verticalPlacement":"FREE","showLabel":true,"shape":null,"layoutText":null}],"mainLabel":115},"orientationAtVertex":"FREE","reference":null}],"reference":null},{"@id":116,"shape":{"type":"rectangle","xposition":"NaN","yposition":"NaN","width":"NaN","height":"NaN","color":{"argb":"ff000000"}},"labelManager":{"labels":[{"type":"text","@id":117,"inputText":"eafd3f014b79f3e2","font":{"fontName":"SansSerif.plain","style":0,"size":10},"noBreak":false,"color":{"argb":"ff000000"},"placement":"FREE","horizontalPlacement":"FREE","verticalPlacement":"FREE","showLabel":true,"shape":null,"layoutText":null}],"mainLabel":117},"portCompositions":[{"type":"portGroup","@id":118,"ordered":false,"portCompositions":[{"type":"port","@id":119,"shape":{"type":"rectangle","xposition":"NaN","yposition":"NaN","width":"NaN","height":"NaN","color":{"argb":"ff000000"}},"labelManager":{"labels":[{"type":"text","@id":120,"inputText":"A.1","font":{"fontName":"SansSerif.plain","style":0,"size":10},"noBreak":false,"color":{"argb":"ff000000"},"placement":"FREE","horizontalPlacement":"FREE","verticalPlacement":"FREE","showLabel":true,"shape":null,"layoutText":null}],"mainLabel":120},"orientationAtVertex":"FREE","reference":null}],"reference":null}],"reference":null},{"@id":121,"shape":{"type":"rectangle","xposition":"NaN","yposition":"NaN","width":"NaN","height":"NaN","color":{"argb":"ff000000"}},"labelManager":{"labels":[{"type":"text","@id":122,"inputText":"609538128454dd9b","font":{"fontName":"SansSerif.plain","style":0,"size":10},"noBreak":false,"color":{"argb":"ff000000"},"placement":"FREE","horizontalPlacement":"FREE","verticalPlacement":"FREE","showLabel":true,"shape":null,"layoutText":null}],"mainLabel":122},"portCompositions":[{"type":"portGroup","@id":123,"ordered":false,"portCompositions":[{"type":"port","@id":124,"shape":{"type":"rectangle","xposition":"NaN","yposition":"NaN","width":"NaN","height":"NaN","color":{"argb":"ff000000"}},"labelManager":{"labels":[{"type":"text","@id":125,"inputText":"B.1","font":{"fontName":"SansSerif.plain","style":0,"size":10},"noBreak":false,"color":{"argb":"ff000000"},"placement":"FREE","horizontalPlacement":"FREE","verticalPlacement":"FREE","showLabel":true,"shape":null,"layoutText":null}],"mainLabel":125},"orientationAtVertex":"FREE","reference":null}],"reference":null}],"reference":null},{"@id":126,"shape":{"type":"rectangle","xposition":"NaN","yposition":"NaN","width":"NaN","height":"NaN","color":{"argb":"ff000000"}},"labelManager":{"labels":[{"type":"text","@id":127,"inputText":"e9800998ecf8427e","font":{"fontName":"SansSerif.plain","style":0,"size":10},"noBreak":false,"color":{"argb":"ff000000"},"placement":"FREE","horizontalPlacement":"FREE","verticalPlacement":"FREE","showLabel":true,"shape":null,"layoutText":null}],"mainLabel":127},"portCompositions":[{"type":"port","@id":128,"shape":{"type":"rectangle","xposition":"NaN","yposition":"NaN","width":"NaN","height":"NaN","color":{"argb":"ff000000"}},"labelManager":{"labels":[{"type":"text","@id":129,"inputText":"","font":{"fontName":"SansSerif.plain","style":0,"size":10},"noBreak":false,"color":{"argb":"ff000000"},"placement":"FREE","horizontalPlacement":"FREE","verticalPlacement":"FREE","showLabel":true,"shape":null,"layoutText":null}],"mainLabel":129},"orientationAtVertex":"FREE","reference":null}],"reference":null},{"@id":130,"shape":{"type":"rectangle","xposition":"NaN","yposition":"NaN","width":"NaN","height":"NaN","color":{"argb":"ff000000"}},"labelManager":{"labels":[{"type":"text","@id":131,"inputText":"72798433f18b35e2","font":{"fontName":"SansSerif.plain","style":0,"size":10},"noBreak":false,"color":{"argb":"ff000000"},"placement":"FREE","horizontalPlacement":"FREE","verticalPlacement":"FREE","showLabel":true,"shape":null,"layoutText":null}],"mainLabel":131},"portCompositions":[{"type":"portGroup","@id":132,"ordered":false,"portCompositions":[{"type":"port","@id":133,"shape":{"type":"rectangle","xposition":"NaN","yposition":"NaN","width":"NaN","height":"NaN","color":{"argb":"ff000000"}},"labelManager":{"labels":[{"type":"text","@id":134,"inputText":"A.4","font":{"fontName":"SansSerif.plain","style":0,"size":10},"noBreak":false,"color":{"argb":"ff000000"},"placement":"FREE","horizontalPlacement":"FREE","verticalPlacement":"FREE","showLabel":true,"shape":null,"layoutText":null}],"mainLabel":134},"orientationAtVertex":"FREE","reference":null},{"type":"port","@id":135,"shape":{"type":"rectangle","xposition":"NaN","yposition":"NaN","width":"NaN","height":"NaN","color":{"argb":"ff000000"}},"labelManager":{"labels":[{"type":"text","@id":136,"inputText":"A.3","font":{"fontName":"SansSerif.plain","style":0,"size":10},"noBreak":false,"color":{"argb":"ff000000"},"placement":"FREE","horizontalPlacement":"FREE","verticalPlacement":"FREE","showLabel":true,"shape":null,"layoutText":null}],"mainLabel":136},"orientationAtVertex":"FREE","reference":null},{"type":"port","@id":137,"shape":{"type":"rectangle","xposition":"NaN","yposition":"NaN","width":"NaN","height":"NaN","color":{"argb":"ff000000"}},"labelManager":{"labels":[{"type":"text","@id":138,"inputText":"A.2","font":{"fontName":"SansSerif.plain","style":0,"size":10},"noBreak":false,"color":{"argb":"ff000000"},"placement":"FREE","horizontalPlacement":"FREE","verticalPlacement":"FREE","showLabel":true,"shape":null,"layoutText":null}],"mainLabel":138},"orientationAtVertex":"FREE","reference":null},{"type":"port","@id":139,"shape":{"type":"rectangle","xposition":"NaN","yposition":"NaN","width":"NaN","height":"NaN","color":{"argb":"ff000000"}},"labelManager":{"labels":[{"type":"text","@id":140,"inputText":"A.1","font":{"fontName":"SansSerif.plain","style":0,"size":10},"noBreak":false,"color":{"argb":"ff000000"},"placement":"FREE","horizontalPlacement":"FREE","verticalPlacement":"FREE","showLabel":true,"shape":null,"layoutText":null}],"mainLabel":140},"orientationAtVertex":"FREE","reference":null}],"reference":null}],"reference":null},{"@id":141,"shape":{"type":"rectangle","xposition":"NaN","yposition":"NaN","width":"NaN","height":"NaN","color":{"argb":"ff000000"}},"labelManager":{"labels":[{"type":"text","@id":142,"inputText":"befd2f6e57e8739a","font":{"fontName":"SansSerif.plain","style":0,"size":10},"noBreak":false,"color":{"argb":"ff000000"},"placement":"FREE","horizontalPlacement":"FREE","verticalPlacement":"FREE","showLabel":true,"shape":null,"layoutText":null}],"mainLabel":142},"portCompositions":[{"type":"portGroup","@id":143,"ordered":false,"portCompositions":[{"type":"port","@id":144,"shape":{"type":"rectangle","xposition":"NaN","yposition":"NaN","width":"NaN","height":"NaN","color":{"argb":"ff000000"}},"labelManager":{"labels":[{"type":"text","@id":145,"inputText":"B.4","font":{"fontName":"SansSerif.plain","style":0,"size":10},"noBreak":false,"color":{"argb":"ff000000"},"placement":"FREE","horizontalPlacement":"FREE","verticalPlacement":"FREE","showLabel":true,"shape":null,"layoutText":null}],"mainLabel":145},"orientationAtVertex":"FREE","reference":null},{"type":"port","@id":146,"shape":{"type":"rectangle","xposition":"NaN","yposition":"NaN","width":"NaN","height":"NaN","color":{"argb":"ff000000"}},"labelManager":{"labels":[{"type":"text","@id":147,"inputText":"B.3","font":{"fontName":"SansSerif.plain","style":0,"size":10},"noBreak":false,"color":{"argb":"ff000000"},"placement":"FREE","horizontalPlacement":"FREE","verticalPlacement":"FREE","showLabel":true,"shape":null,"layoutText":null}],"mainLabel":147},"orientationAtVertex":"FREE","reference":null},{"type":"port","@id":148,"shape":{"type":"rectangle","xposition":"NaN","yposition":"NaN","width":"NaN","height":"NaN","color":{"argb":"ff000000"}},"labelManager":{"labels":[{"type":"text","@id":149,"inputText":"B.2","font":{"fontName":"SansSerif.plain","style":0,"size":10},"noBreak":false,"color":{"argb":"ff000000"},"placement":"FREE","horizontalPlacement":"FREE","verticalPlacement":"FREE","showLabel":true,"shape":null,"layoutText":null}],"mainLabel":149},"orientationAtVertex":"FREE","reference":null},{"type":"port","@id":150,"shape":{"type":"rectangle","xposition":"NaN","yposition":"NaN","width":"NaN","height":"NaN","color":{"argb":"ff000000"}},"labelManager":{"labels":[{"type":"text","@id":151,"inputText":"B.1","font":{"fontName":"SansSerif.plain","style":0,"size":10},"noBreak":false,"color":{"argb":"ff000000"},"placement":"FREE","horizontalPlacement":"FREE","verticalPlacement":"FREE","showLabel":true,"shape":null,"layoutText":null}],"mainLabel":151},"orientationAtVertex":"FREE","reference":null}],"reference":null}],"reference":null},{"@id":152,"shape":null,"labelManager":{"labels":[{"type":"text","@id":153,"inputText":"e9800998ecf8427e","font":{"fontName":"SansSerif.plain","style":0,"size":10},"noBreak":false,"color":{"argb":"ff000000"},"placement":"FREE","horizontalPlacement":"FREE","verticalPlacement":"FREE","showLabel":true,"shape":null,"layoutText":null}],"mainLabel":153},"portCompositions":[{"type":"port","@id":154,"shape":{"type":"rectangle","xposition":"NaN","yposition":"NaN","width":"NaN","height":"NaN","color":{"argb":"ff000000"}},"labelManager":{"labels":[{"type":"text","@id":155,"inputText":"","font":{"fontName":"SansSerif.plain","style":0,"size":10},"noBreak":false,"color":{"argb":"ff000000"},"placement":"FREE","horizontalPlacement":"FREE","verticalPlacement":"FREE","showLabel":true,"shape":null,"layoutText":null}],"mainLabel":155},"orientationAtVertex":"FREE","reference":null}],"reference":null},{"@id":156,"shape":null,"labelManager":{"labels":[{"type":"text","@id":157,"inputText":"e9800998ecf8427e","font":{"fontName":"SansSerif.plain","style":0,"size":10},"noBreak":false,"color":{"argb":"ff000000"},"placement":"FREE","horizontalPlacement":"FREE","verticalPlacement":"FREE","showLabel":true,"shape":null,"layoutText":null}],"mainLabel":157},"portCompositions":[{"type":"port","@id":158,"shape":{"type":"rectangle","xposition":"NaN","yposition":"NaN","width":"NaN","height":"NaN","color":{"argb":"ff000000"}},"labelManager":{"labels":[{"type":"text","@id":159,"inputText":"","font":{"fontName":"SansSerif.plain","style":0,"size":10},"noBreak":false,"color":{"argb":"ff000000"},"placement":"FREE","horizontalPlacement":"FREE","verticalPlacement":"FREE","showLabel":true,"shape":null,"layoutText":null}],"mainLabel":159},"orientationAtVertex":"FREE","reference":null}],"reference":null},{"@id":160,"shape":null,"labelManager":{"labels":[{"type":"text","@id":161,"inputText":"e9800998ecf8427e","font":{"fontName":"SansSerif.plain","style":0,"size":10},"noBreak":false,"color":{"argb":"ff000000"},"placement":"FREE","horizontalPlacement":"FREE","verticalPlacement":"FREE","showLabel":true,"shape":null,"layoutText":null}],"mainLabel":161},"portCompositions":[{"type":"port","@id":162,"shape":{"type":"rectangle","xposition":"NaN","yposition":"NaN","width":"NaN","height":"NaN","color":{"argb":"ff000000"}},"labelManager":{"labels":[{"type":"text","@id":163,"inputText":"","font":{"fontName":"SansSerif.plain","style":0,"size":10},"noBreak":false,"color":{"argb":"ff000000"},"placement":"FREE","horizontalPlacement":"FREE","verticalPlacement":"FREE","showLabel":true,"shape":null,"layoutText":null}],"mainLabel":163},"orientationAtVertex":"FREE","reference":null}],"reference":null},{"@id":164,"shape":null,"labelManager":{"labels":[{"type":"text","@id":165,"inputText":"e9800998ecf8427e","font":{"fontName":"SansSerif.plain","style":0,"size":10},"noBreak":false,"color":{"argb":"ff000000"},"placement":"FREE","horizontalPlacement":"FREE","verticalPlacement":"FREE","showLabel":true,"shape":null,"layoutText":null}],"mainLabel":165},"portCompositions":[{"type":"port","@id":166,"shape":{"type":"rectangle","xposition":"NaN","yposition":"NaN","width":"NaN","height":"NaN","color":{"argb":"ff000000"}},"labelManager":{"labels":[{"type":"text","@id":167,"inputText":"","font":{"fontName":"SansSerif.plain","style":0,"size":10},"noBreak":false,"color":{"argb":"ff000000"},"placement":"FREE","horizontalPlacement":"FREE","verticalPlacement":"FREE","showLabel":true,"shape":null,"layoutText":null}],"mainLabel":167},"orientationAtVertex":"FREE","reference":null}],"reference":null},{"@id":168,"shape":null,"labelManager":{"labels":[{"type":"text","@id":169,"inputText":"e9800998ecf8427e","font":{"fontName":"SansSerif.plain","style":0,"size":10},"noBreak":false,"color":{"argb":"ff000000"},"placement":"FREE","horizontalPlacement":"FREE","verticalPlacement":"FREE","showLabel":true,"shape":null,"layoutText":null}],"mainLabel":169},"portCompositions":[{"type":"port","@id":170,"shape":{"type":"rectangle","xposition":"NaN","yposition":"NaN","width":"NaN","height":"NaN","color":{"argb":"ff000000"}},"labelManager":{"labels":[{"type":"text","@id":171,"inputText":"","font":{"fontName":"SansSerif.plain","style":0,"size":10},"noBreak":false,"color":{"argb":"ff000000"},"placement":"FREE","horizontalPlacement":"FREE","verticalPlacement":"FREE","showLabel":true,"shape":null,"layoutText":null}],"mainLabel":171},"orientationAtVertex":"FREE","reference":null}],"reference":null},{"@id":172,"shape":null,"labelManager":{"labels":[{"type":"text","@id":173,"inputText":"e9800998ecf8427e","font":{"fontName":"SansSerif.plain","style":0,"size":10},"noBreak":false,"color":{"argb":"ff000000"},"placement":"FREE","horizontalPlacement":"FREE","verticalPlacement":"FREE","showLabel":true,"shape":null,"layoutText":null}],"mainLabel":173},"portCompositions":[{"type":"port","@id":174,"shape":{"type":"rectangle","xposition":"NaN","yposition":"NaN","width":"NaN","height":"NaN","color":{"argb":"ff000000"}},"labelManager":{"labels":[{"type":"text","@id":175,"inputText":"","font":{"fontName":"SansSerif.plain","style":0,"size":10},"noBreak":false,"color":{"argb":"ff000000"},"placement":"FREE","horizontalPlacement":"FREE","verticalPlacement":"FREE","showLabel":true,"shape":null,"layoutText":null}],"mainLabel":175},"orientationAtVertex":"FREE","reference":null}],"reference":null},{"@id":176,"shape":null,"labelManager":{"labels":[{"type":"text","@id":177,"inputText":"e9800998ecf8427e","font":{"fontName":"SansSerif.plain","style":0,"size":10},"noBreak":false,"color":{"argb":"ff000000"},"placement":"FREE","horizontalPlacement":"FREE","verticalPlacement":"FREE","showLabel":true,"shape":null,"layoutText":null}],"mainLabel":177},"portCompositions":[{"type":"port","@id":178,"shape":{"type":"rectangle","xposition":"NaN","yposition":"NaN","width":"NaN","height":"NaN","color":{"argb":"ff000000"}},"labelManager":{"labels":[{"type":"text","@id":179,"inputText":"","font":{"fontName":"SansSerif.plain","style":0,"size":10},"noBreak":false,"color":{"argb":"ff000000"},"placement":"FREE","horizontalPlacement":"FREE","verticalPlacement":"FREE","showLabel":true,"shape":null,"layoutText":null}],"mainLabel":179},"orientationAtVertex":"FREE","reference":null}],"reference":null},{"@id":180,"shape":null,"labelManager":{"labels":[{"type":"text","@id":181,"inputText":"e9800998ecf8427e","font":{"fontName":"SansSerif.plain","style":0,"size":10},"noBreak":false,"color":{"argb":"ff000000"},"placement":"FREE","horizontalPlacement":"FREE","verticalPlacement":"FREE","showLabel":true,"shape":null,"layoutText":null}],"mainLabel":181},"portCompositions":[{"type":"port","@id":182,"shape":{"type":"rectangle","xposition":"NaN","yposition":"NaN","width":"NaN","height":"NaN","color":{"argb":"ff000000"}},"labelManager":{"labels":[{"type":"text","@id":183,"inputText":"","font":{"fontName":"SansSerif.plain","style":0,"size":10},"noBreak":false,"color":{"argb":"ff000000"},"placement":"FREE","horizontalPlacement":"FREE","verticalPlacement":"FREE","showLabel":true,"shape":null,"layoutText":null}],"mainLabel":183},"orientationAtVertex":"FREE","reference":null}],"reference":null},{"@id":184,"shape":null,"labelManager":{"labels":[{"type":"text","@id":185,"inputText":"e9800998ecf8427e","font":{"fontName":"SansSerif.plain","style":0,"size":10},"noBreak":false,"color":{"argb":"ff000000"},"placement":"FREE","horizontalPlacement":"FREE","verticalPlacement":"FREE","showLabel":true,"shape":null,"layoutText":null}],"mainLabel":185},"portCompositions":[{"type":"port","@id":186,"shape":{"type":"rectangle","xposition":"NaN","yposition":"NaN","width":"NaN","height":"NaN","color":{"argb":"ff000000"}},"labelManager":{"labels":[{"type":"text","@id":187,"inputText":"","font":{"fontName":"SansSerif.plain","style":0,"size":10},"noBreak":false,"color":{"argb":"ff000000"},"placement":"FREE","horizontalPlacement":"FREE","verticalPlacement":"FREE","showLabel":true,"shape":null,"layoutText":null}],"mainLabel":187},"orientationAtVertex":"FREE","reference":null}],"reference":null},{"@id":188,"shape":null,"labelManager":{"labels":[{"type":"text","@id":189,"inputText":"e9800998ecf8427e","font":{"fontName":"SansSerif.plain","style":0,"size":10},"noBreak":false,"color":{"argb":"ff000000"},"placement":"FREE","horizontalPlacement":"FREE","verticalPlacement":"FREE","showLabel":true,"shape":null,"layoutText":null}],"mainLabel":189},"portCompositions":[{"type":"port","@id":190,"shape":{"type":"rectangle","xposition":"NaN","yposition":"NaN","width":"NaN","height":"NaN","color":{"argb":"ff000000"}},"labelManager":{"labels":[{"type":"text","@id":191,"inputText":"","font":{"fontName":"SansSerif.plain","style":0,"size":10},"noBreak":false,"color":{"argb":"ff000000"},"placement":"FREE","horizontalPlacement":"FREE","verticalPlacement":"FREE","showLabel":true,"shape":null,"layoutText":null}],"mainLabel":191},"orientationAtVertex":"FREE","reference":null}],"reference":null},{"@id":192,"shape":null,"labelManager":{"labels":[{"type":"text","@id":193,"inputText":"734050ccf0531117","font":{"fontName":"SansSerif.plain","style":0,"size":10},"noBreak":false,"color":{"argb":"ff000000"},"placement":"FREE","horizontalPlacement":"FREE","verticalPlacement":"FREE","showLabel":true,"shape":null,"layoutText":null}],"mainLabel":193},"portCompositions":[{"type":"portGroup","@id":194,"ordered":false,"portCompositions":[{"type":"port","@id":195,"shape":{"type":"rectangle","xposition":"NaN","yposition":"NaN","width":"NaN","height":"NaN","color":{"argb":"ff000000"}},"labelManager":{"labels":[{"type":"text","@id":196,"inputText":"A.1","font":{"fontName":"SansSerif.plain","style":0,"size":10},"noBreak":false,"color":{"argb":"ff000000"},"placement":"FREE","horizontalPlacement":"FREE","verticalPlacement":"FREE","showLabel":true,"shape":null,"layoutText":null}],"mainLabel":196},"orientationAtVertex":"FREE","reference":null}],"reference":null}],"reference":null},{"@id":197,"shape":null,"labelManager":{"labels":[{"type":"text","@id":198,"inputText":"1e44b5110d8a6278","font":{"fontName":"SansSerif.plain","style":0,"size":10},"noBreak":false,"color":{"argb":"ff000000"},"placement":"FREE","horizontalPlacement":"FREE","verticalPlacement":"FREE","showLabel":true,"shape":null,"layoutText":null}],"mainLabel":198},"portCompositions":[{"type":"portGroup","@id":199,"ordered":false,"portCompositions":[{"type":"port","@id":200,"shape":{"type":"rectangle","xposition":"NaN","yposition":"NaN","width":"NaN","height":"NaN","color":{"argb":"ff000000"}},"labelManager":{"labels":[{"type":"text","@id":201,"inputText":"B.1","font":{"fontName":"SansSerif.plain","style":0,"size":10},"noBreak":false,"color":{"argb":"ff000000"},"placement":"FREE","horizontalPlacement":"FREE","verticalPlacement":"FREE","showLabel":true,"shape":null,"layoutText":null}],"mainLabel":201},"orientationAtVertex":"FREE","reference":null}],"reference":null}],"reference":null},{"@id":202,"shape":null,"labelManager":{"labels":[{"type":"text","@id":203,"inputText":"b34a6420f02161b4","font":{"fontName":"SansSerif.plain","style":0,"size":10},"noBreak":false,"color":{"argb":"ff000000"},"placement":"FREE","horizontalPlacement":"FREE","verticalPlacement":"FREE","showLabel":true,"shape":null,"layoutText":null}],"mainLabel":203},"portCompositions":[{"type":"portGroup","@id":204,"ordered":false,"portCompositions":[{"type":"port","@id":205,"shape":{"type":"rectangle","xposition":"NaN","yposition":"NaN","width":"NaN","height":"NaN","color":{"argb":"ff000000"}},"labelManager":{"labels":[{"type":"text","@id":206,"inputText":"A.1","font":{"fontName":"SansSerif.plain","style":0,"size":10},"noBreak":false,"color":{"argb":"ff000000"},"placement":"FREE","horizontalPlacement":"FREE","verticalPlacement":"FREE","showLabel":true,"shape":null,"layoutText":null}],"mainLabel":206},"orientationAtVertex":"FREE","reference":null}],"reference":null}],"reference":null},{"@id":207,"shape":null,"labelManager":{"labels":[{"type":"text","@id":208,"inputText":"82084e0fd8c5c30a","font":{"fontName":"SansSerif.plain","style":0,"size":10},"noBreak":false,"color":{"argb":"ff000000"},"placement":"FREE","horizontalPlacement":"FREE","verticalPlacement":"FREE","showLabel":true,"shape":null,"layoutText":null}],"mainLabel":208},"portCompositions":[{"type":"portGroup","@id":209,"ordered":false,"portCompositions":[{"type":"port","@id":210,"shape":{"type":"rectangle","xposition":"NaN","yposition":"NaN","width":"NaN","height":"NaN","color":{"argb":"ff000000"}},"labelManager":{"labels":[{"type":"text","@id":211,"inputText":"B.1","font":{"fontName":"SansSerif.plain","style":0,"size":10},"noBreak":false,"color":{"argb":"ff000000"},"placement":"FREE","horizontalPlacement":"FREE","verticalPlacement":"FREE","showLabel":true,"shape":null,"layoutText":null}],"mainLabel":211},"orientationAtVertex":"FREE","reference":null}],"reference":null}],"reference":null},{"@id":212,"shape":null,"labelManager":{"labels":[{"type":"text","@id":213,"inputText":"21aa99bc6f54d131","font":{"fontName":"SansSerif.plain","style":0,"size":10},"noBreak":false,"color":{"argb":"ff000000"},"placement":"FREE","horizontalPlacement":"FREE","verticalPlacement":"FREE","showLabel":true,"shape":null,"layoutText":null}],"mainLabel":213},"portCompositions":[{"type":"portGroup","@id":214,"ordered":false,"portCompositions":[{"type":"port","@id":215,"shape":{"type":"rectangle","xposition":"NaN","yposition":"NaN","width":"NaN","height":"NaN","color":{"argb":"ff000000"}},"labelManager":{"labels":[{"type":"text","@id":216,"inputText":"A.1","font":{"fontName":"SansSerif.plain","style":0,"size":10},"noBreak":false,"color":{"argb":"ff000000"},"placement":"FREE","horizontalPlacement":"FREE","verticalPlacement":"FREE","showLabel":true,"shape":null,"layoutText":null}],"mainLabel":216},"orientationAtVertex":"FREE","reference":null},{"type":"port","@id":217,"shape":{"type":"rectangle","xposition":"NaN","yposition":"NaN","width":"NaN","height":"NaN","color":{"argb":"ff000000"}},"labelManager":{"labels":[{"type":"text","@id":218,"inputText":"A.2","font":{"fontName":"SansSerif.plain","style":0,"size":10},"noBreak":false,"color":{"argb":"ff000000"},"placement":"FREE","horizontalPlacement":"FREE","verticalPlacement":"FREE","showLabel":true,"shape":null,"layoutText":null}],"mainLabel":218},"orientationAtVertex":"FREE","reference":null}],"reference":null}],"reference":null},{"@id":219,"shape":null,"labelManager":{"labels":[{"type":"text","@id":220,"inputText":"b15c86de218f03d7","font":{"fontName":"SansSerif.plain","style":0,"size":10},"noBreak":false,"color":{"argb":"ff000000"},"placement":"FREE","horizontalPlacement":"FREE","verticalPlacement":"FREE","showLabel":true,"shape":null,"layoutText":null}],"mainLabel":220},"portCompositions":[{"type":"portGroup","@id":221,"ordered":false,"portCompositions":[{"type":"port","@id":222,"shape":{"type":"rectangle","xposition":"NaN","yposition":"NaN","width":"NaN","height":"NaN","color":{"argb":"ff000000"}},"labelManager":{"labels":[{"type":"text","@id":223,"inputText":"B.1","font":{"fontName":"SansSerif.plain","style":0,"size":10},"noBreak":false,"color":{"argb":"ff000000"},"placement":"FREE","horizontalPlacement":"FREE","verticalPlacement":"FREE","showLabel":true,"shape":null,"layoutText":null}],"mainLabel":223},"orientationAtVertex":"FREE","reference":null},{"type":"port","@id":224,"shape":{"type":"rectangle","xposition":"NaN","yposition":"NaN","width":"NaN","height":"NaN","color":{"argb":"ff000000"}},"labelManager":{"labels":[{"type":"text","@id":225,"inputText":"B.2","font":{"fontName":"SansSerif.plain","style":0,"size":10},"noBreak":false,"color":{"argb":"ff000000"},"placement":"FREE","horizontalPlacement":"FREE","verticalPlacement":"FREE","showLabel":true,"shape":null,"layoutText":null}],"mainLabel":225},"orientationAtVertex":"FREE","reference":null}],"reference":null}],"reference":null},{"@id":226,"shape":null,"labelManager":{"labels":[{"type":"text","@id":227,"inputText":"f0584236f061a433","font":{"fontName":"SansSerif.plain","style":0,"size":10},"noBreak":false,"color":{"argb":"ff000000"},"placement":"FREE","horizontalPlacement":"FREE","verticalPlacement":"FREE","showLabel":true,"shape":null,"layoutText":null}],"mainLabel":227},"portCompositions":[{"type":"portGroup","@id":228,"ordered":false,"portCompositions":[{"type":"port","@id":229,"shape":{"type":"rectangle","xposition":"NaN","yposition":"NaN","width":"NaN","height":"NaN","color":{"argb":"ff000000"}},"labelManager":{"labels":[{"type":"text","@id":230,"inputText":"A.3","font":{"fontName":"SansSerif.plain","style":0,"size":10},"noBreak":false,"color":{"argb":"ff000000"},"placement":"FREE","horizontalPlacement":"FREE","verticalPlacement":"FREE","showLabel":true,"shape":null,"layoutText":null}],"mainLabel":230},"orientationAtVertex":"FREE","reference":null},{"type":"port","@id":231,"shape":{"type":"rectangle","xposition":"NaN","yposition":"NaN","width":"NaN","height":"NaN","color":{"argb":"ff000000"}},"labelManager":{"labels":[{"type":"text","@id":232,"inputText":"A.1","font":{"fontName":"SansSerif.plain","style":0,"size":10},"noBreak":false,"color":{"argb":"ff000000"},"placement":"FREE","horizontalPlacement":"FREE","verticalPlacement":"FREE","showLabel":true,"shape":null,"layoutText":null}],"mainLabel":232},"orientationAtVertex":"FREE","reference":null},{"type":"port","@id":233,"shape":{"type":"rectangle","xposition":"NaN","yposition":"NaN","width":"NaN","height":"NaN","color":{"argb":"ff000000"}},"labelManager":{"labels":[{"type":"text","@id":234,"inputText":"A.4","font":{"fontName":"SansSerif.plain","style":0,"size":10},"noBreak":false,"color":{"argb":"ff000000"},"placement":"FREE","horizontalPlacement":"FREE","verticalPlacement":"FREE","showLabel":true,"shape":null,"layoutText":null}],"mainLabel":234},"orientationAtVertex":"FREE","reference":null},{"type":"port","@id":235,"shape":{"type":"rectangle","xposition":"NaN","yposition":"NaN","width":"NaN","height":"NaN","color":{"argb":"ff000000"}},"labelManager":{"labels":[{"type":"text","@id":236,"inputText":"A.2","font":{"fontName":"SansSerif.plain","style":0,"size":10},"noBreak":false,"color":{"argb":"ff000000"},"placement":"FREE","horizontalPlacement":"FREE","verticalPlacement":"FREE","showLabel":true,"shape":null,"layoutText":null}],"mainLabel":236},"orientationAtVertex":"FREE","reference":null}],"reference":null}],"reference":null},{"@id":237,"shape":null,"labelManager":{"labels":[{"type":"text","@id":238,"inputText":"2fb0c507413db72f","font":{"fontName":"SansSerif.plain","style":0,"size":10},"noBreak":false,"color":{"argb":"ff000000"},"placement":"FREE","horizontalPlacement":"FREE","verticalPlacement":"FREE","showLabel":true,"shape":null,"layoutText":null}],"mainLabel":238},"portCompositions":[{"type":"portGroup","@id":239,"ordered":false,"portCompositions":[{"type":"port","@id":240,"shape":{"type":"rectangle","xposition":"NaN","yposition":"NaN","width":"NaN","height":"NaN","color":{"argb":"ff000000"}},"labelManager":{"labels":[{"type":"text","@id":241,"inputText":"B.3","font":{"fontName":"SansSerif.plain","style":0,"size":10},"noBreak":false,"color":{"argb":"ff000000"},"placement":"FREE","horizontalPlacement":"FREE","verticalPlacement":"FREE","showLabel":true,"shape":null,"layoutText":null}],"mainLabel":241},"orientationAtVertex":"FREE","reference":null},{"type":"port","@id":242,"shape":{"type":"rectangle","xposition":"NaN","yposition":"NaN","width":"NaN","height":"NaN","color":{"argb":"ff000000"}},"labelManager":{"labels":[{"type":"text","@id":243,"inputText":"B.1","font":{"fontName":"SansSerif.plain","style":0,"size":10},"noBreak":false,"color":{"argb":"ff000000"},"placement":"FREE","horizontalPlacement":"FREE","verticalPlacement":"FREE","showLabel":true,"shape":null,"layoutText":null}],"mainLabel":243},"orientationAtVertex":"FREE","reference":null},{"type":"port","@id":244,"shape":{"type":"rectangle","xposition":"NaN","yposition":"NaN","width":"NaN","height":"NaN","color":{"argb":"ff000000"}},"labelManager":{"labels":[{"type":"text","@id":245,"inputText":"B.4","font":{"fontName":"SansSerif.plain","style":0,"size":10},"noBreak":false,"color":{"argb":"ff000000"},"placement":"FREE","horizontalPlacement":"FREE","verticalPlacement":"FREE","showLabel":true,"shape":null,"layoutText":null}],"mainLabel":245},"orientationAtVertex":"FREE","reference":null},{"type":"port","@id":246,"shape":{"type":"rectangle","xposition":"NaN","yposition":"NaN","width":"NaN","height":"NaN","color":{"argb":"ff000000"}},"labelManager":{"labels":[{"type":"text","@id":247,"inputText":"B.2","font":{"fontName":"SansSerif.plain","style":0,"size":10},"noBreak":false,"color":{"argb":"ff000000"},"placement":"FREE","horizontalPlacement":"FREE","verticalPlacement":"FREE","showLabel":true,"shape":null,"layoutText":null}],"mainLabel":247},"orientationAtVertex":"FREE","reference":null}],"reference":null}],"reference":null}],"vertexGroups":[{"@id":248,"drawnFrame":false,"labelManager":{"labels":[],"mainLabel":null},"shape":null,"containedVertices":[1,8],"containedVertexGroups":[],"touchingPairs":[{"vertex0":1,"horizontalPlacementVertex0":"FREE","verticalPlacementVertex0":"TOP","vertex1":8,"horizontalPlacementVertex1":"FREE","verticalPlacementVertex1":"FREE"}],"portPairings":[{"port0":6,"port1":13},{"port0":4,"port1":11}],"reference":null},{"@id":249,"drawnFrame":false,"labelManager":{"labels":[],"mainLabel":null},"shape":null,"containedVertices":[15,22],"containedVertexGroups":[],"touchingPairs":[{"vertex0":15,"horizontalPlacementVertex0":"FREE","verticalPlacementVertex0":"TOP","vertex1":22,"horizontalPlacementVertex1":"FREE","verticalPlacementVertex1":"FREE"}],"portPairings":[{"port0":18,"port1":25},{"port0":20,"port1":27}],"reference":null},{"@id":250,"drawnFrame":false,"labelManager":{"labels":[],"mainLabel":null},"shape":null,"containedVertices":[29,34],"containedVertexGroups":[],"touchingPairs":[{"vertex0":29,"horizontalPlacementVertex0":"FREE","verticalPlacementVertex0":"TOP","vertex1":34,"horizontalPlacementVertex1":"FREE","verticalPlacementVertex1":"FREE"}],"portPairings":[{"port0":32,"port1":37}],"reference":null},{"@id":251,"drawnFrame":false,"labelManager":{"labels":[],"mainLabel":null},"shape":null,"containedVertices":[39,44],"containedVertexGroups":[],"touchingPairs":[{"vertex0":39,"horizontalPlacementVertex0":"FREE","verticalPlacementVertex0":"TOP","vertex1":44,"horizontalPlacementVertex1":"FREE","verticalPlacementVertex1":"FREE"}],"portPairings":[{"port0":42,"port1":47}],"reference":null},{"@id":252,"drawnFrame":false,"labelManager":{"labels":[],"mainLabel":null},"shape":null,"containedVertices":[49,62],"containedVertexGroups":[],"touchingPairs":[{"vertex0":49,"horizontalPlacementVertex0":"FREE","verticalPlacementVertex0":"TOP","vertex1":62,"horizontalPlacementVertex1":"FREE","verticalPlacementVertex1":"FREE"}],"portPairings":[{"port0":52,"port1":65},{"port0":54,"port1":67},{"port0":56,"port1":69},{"port0":58,"port1":71},{"port0":60,"port1":73}],"reference":null},{"@id":253,"drawnFrame":false,"labelManager":{"labels":[],"mainLabel":null},"shape":null,"containedVertices":[79,90],"containedVertexGroups":[],"touchingPairs":[{"vertex0":79,"horizontalPlacementVertex0":"FREE","verticalPlacementVertex0":"TOP","vertex1":90,"horizontalPlacementVertex1":"FREE","verticalPlacementVertex1":"FREE"}],"portPairings":[{"port0":88,"port1":99},{"port0":82,"port1":93},{"port0":86,"port1":97},{"port0":84,"port1":95}],"reference":null},{"@id":254,"drawnFrame":false,"labelManager":{"labels":[],"mainLabel":null},"shape":null,"containedVertices":[101,107],"containedVertexGroups":[],"touchingPairs":[{"vertex0":101,"horizontalPlacementVertex0":"FREE","verticalPlacementVertex0":"TOP","vertex1":107,"horizontalPlacementVertex1":"FREE","verticalPlacementVertex1":"FREE"}],"portPairings":[{"port0":105,"port1":110}],"reference":null},{"@id":255,"drawnFrame":false,"labelManager":{"labels":[],"mainLabel":null},"shape":null,"containedVertices":[116,121],"containedVertexGroups":[],"touchingPairs":[{"vertex0":116,"horizontalPlacementVertex0":"FREE","verticalPlacementVertex0":"TOP","vertex1":121,"horizontalPlacementVertex1":"FREE","verticalPlacementVertex1":"FREE"}],"portPairings":[{"port0":119,"port1":124}],"reference":null},{"@id":256,"drawnFrame":false,"labelManager":{"labels":[],"mainLabel":null},"shape":null,"containedVertices":[130,141],"containedVertexGroups":[],"touchingPairs":[{"vertex0":130,"horizontalPlacementVertex0":"FREE","verticalPlacementVertex0":"TOP","vertex1":141,"horizontalPlacementVertex1":"FREE","verticalPlacementVertex1":"FREE"}],"portPairings":[{"port0":135,"port1":146},{"port0":137,"port1":148},{"port0":133,"port1":144},{"port0":139,"port1":150}],"reference":null},{"@id":257,"drawnFrame":false,"labelManager":{"labels":[],"mainLabel":null},"shape":null,"containedVertices":[192,197],"containedVertexGroups":[],"touchingPairs":[{"vertex0":192,"horizontalPlacementVertex0":"FREE","verticalPlacementVertex0":"FREE","vertex1":197,"horizontalPlacementVertex1":"FREE","verticalPlacementVertex1":"FREE"}],"portPairings":[{"port0":195,"port1":200}],"reference":null},{"@id":258,"drawnFrame":false,"labelManager":{"labels":[],"mainLabel":null},"shape":null,"containedVertices":[202,207],"containedVertexGroups":[],"touchingPairs":[{"vertex0":202,"horizontalPlacementVertex0":"FREE","verticalPlacementVertex0":"FREE","vertex1":207,"horizontalPlacementVertex1":"FREE","verticalPlacementVertex1":"FREE"}],"portPairings":[{"port0":205,"port1":210}],"reference":null},{"@id":259,"drawnFrame":false,"labelManager":{"labels":[],"mainLabel":null},"shape":null,"containedVertices":[212,219],"containedVertexGroups":[],"touchingPairs":[{"vertex0":212,"horizontalPlacementVertex0":"FREE","verticalPlacementVertex0":"FREE","vertex1":219,"horizontalPlacementVertex1":"FREE","verticalPlacementVertex1":"FREE"}],"portPairings":[{"port0":215,"port1":222},{"port0":217,"port1":224}],"reference":null},{"@id":260,"drawnFrame":false,"labelManager":{"labels":[],"mainLabel":null},"shape":null,"containedVertices":[226,237],"containedVertexGroups":[],"touchingPairs":[{"vertex0":226,"horizontalPlacementVertex0":"FREE","verticalPlacementVertex0":"FREE","vertex1":237,"horizontalPlacementVertex1":"FREE","verticalPlacementVertex1":"FREE"}],"portPairings":[{"port0":229,"port1":240},{"port0":231,"port1":242},{"port0":233,"port1":244},{"port0":235,"port1":246}],"reference":null}],"edges":[{"@id":261,"ports":[27,11],"labelManager":{"innerLabels":[{"type":"text","@id":262,"inputText":"6163538943142924","font":{"fontName":"SansSerif.plain","style":0,"size":10},"noBreak":false,"color":{"argb":"ff000000"},"placement":"FREE","horizontalPlacement":"FREE","verticalPlacement":"FREE","showLabel":true,"shape":null,"layoutText":null}],"allPortLabels":[],"mainLabel":262},"thickness":-1.0,"color":{"argb":"ff000000"},"paths":[],"reference":null},{"@id":263,"ports":[65,148],"labelManager":{"innerLabels":[{"type":"text","@id":264,"inputText":"34163eab8fc4c9e4","font":{"fontName":"SansSerif.plain","style":0,"size":10},"noBreak":false,"color":{"argb":"ff000000"},"placement":"FREE","horizontalPlacement":"FREE","verticalPlacement":"FREE","showLabel":true,"shape":null,"layoutText":null}],"allPortLabels":[],"mainLabel":264},"thickness":-1.0,"color":{"argb":"ff000000"},"paths":[],"reference":null},{"@id":265,"ports":[4,110],"labelManager":{"innerLabels":[{"type":"text","@id":266,"inputText":"2db69e5893f21e27","font":{"fontName":"SansSerif.plain","style":0,"size":10},"noBreak":false,"color":{"argb":"ff000000"},"placement":"FREE","horizontalPlacement":"FREE","verticalPlacement":"FREE","showLabel":true,"shape":null,"layoutText":null}],"allPortLabels":[],"mainLabel":266},"thickness":-1.0,"color":{"argb":"ff000000"},"paths":[],"reference":null},{"@id":267,"ports":[146,82],"labelManager":{"innerLabels":[{"type":"text","@id":268,"inputText":"0aa4015353bc5844","font":{"fontName":"SansSerif.plain","style":0,"size":10},"noBreak":false,"color":{"argb":"ff000000"},"placement":"FREE","horizontalPlacement":"FREE","verticalPlacement":"FREE","showLabel":true,"shape":null,"layoutText":null}],"allPortLabels":[],"mainLabel":268},"thickness":-1.0,"color":{"argb":"ff000000"},"paths":[],"reference":null},{"@id":269,"ports":[119,47],"labelManager":{"innerLabels":[{"type":"text","@id":270,"inputText":"1e922cd77cecba9a","font":{"fontName":"SansSerif.plain","style":0,"size":10},"noBreak":false,"color":{"argb":"ff000000"},"placement":"FREE","horizontalPlacement":"FREE","verticalPlacement":"FREE","showLabel":true,"shape":null,"layoutText":null}],"allPortLabels":[],"mainLabel":270},"thickness":-1.0,"color":{"argb":"ff000000"},"paths":[],"reference":null},{"@id":271,"ports":[86,67],"labelManager":{"innerLabels":[{"type":"text","@id":272,"inputText":"8133b7c238f114da","font":{"fontName":"SansSerif.plain","style":0,"size":10},"noBreak":false,"color":{"argb":"ff000000"},"placement":"FREE","horizontalPlacement":"FREE","verticalPlacement":"FREE","showLabel":true,"shape":null,"layoutText":null}],"allPortLabels":[],"mainLabel":272},"thickness":-1.0,"color":{"argb":"ff000000"},"paths":[],"reference":null},{"@id":273,"ports":[144,25],"labelManager":{"innerLabels":[{"type":"text","@id":274,"inputText":"6eb9f19227bae981","font":{"fontName":"SansSerif.plain","style":0,"size":10},"noBreak":false,"color":{"argb":"ff000000"},"placement":"FREE","horizontalPlacement":"FREE","verticalPlacement":"FREE","showLabel":true,"shape":null,"layoutText":null}],"allPortLabels":[],"mainLabel":274},"thickness":-1.0,"color":{"argb":"ff000000"},"paths":[],"reference":null},{"@id":275,"ports":[13,84],"labelManager":{"innerLabels":[{"type":"text","@id":276,"inputText":"4dcb9aff48c6edaa","font":{"fontName":"SansSerif.plain","style":0,"size":10},"noBreak":false,"color":{"argb":"ff000000"},"placement":"FREE","horizontalPlacement":"FREE","verticalPlacement":"FREE","showLabel":true,"shape":null,"layoutText":null}],"allPortLabels":[],"mainLabel":276},"thickness":-1.0,"color":{"argb":"ff000000"},"paths":[],"reference":null},{"@id":277,"ports":[154,166],"labelManager":{"innerLabels":[{"type":"text","@id":278,"inputText":"b65b7af1a5272a89","font":{"fontName":"SansSerif.plain","style":0,"size":10},"noBreak":false,"color":{"argb":"ff000000"},"placement":"FREE","horizontalPlacement":"FREE","verticalPlacement":"FREE","showLabel":true,"shape":null,"layoutText":null}],"allPortLabels":[],"mainLabel":278},"thickness":-1.0,"color":{"argb":"ff000000"},"paths":[],"reference":null},{"@id":279,"ports":[205,178],"labelManager":{"innerLabels":[{"type":"text","@id":280,"inputText":"4a2850e34aecd6e1","font":{"fontName":"SansSerif.plain","style":0,"size":10},"noBreak":false,"color":{"argb":"ff000000"},"placement":"FREE","horizontalPlacement":"FREE","verticalPlacement":"FREE","showLabel":true,"shape":null,"layoutText":null}],"allPortLabels":[],"mainLabel":280},"thickness":-1.0,"color":{"argb":"ff000000"},"paths":[],"reference":null},{"@id":281,"ports":[215,170],"labelManager":{"innerLabels":[{"type":"text","@id":282,"inputText":"a81738b28976a895","font":{"fontName":"SansSerif.plain","style":0,"size":10},"noBreak":false,"color":{"argb":"ff000000"},"placement":"FREE","horizontalPlacement":"FREE","verticalPlacement":"FREE","showLabel":true,"shape":null,"layoutText":null}],"allPortLabels":[],"mainLabel":282},"thickness":-1.0,"color":{"argb":"ff000000"},"paths":[],"reference":null},{"@id":283,"ports":[154,114],"labelManager":{"innerLabels":[{"type":"text","@id":284,"inputText":"749735235479c2b3","font":{"fontName":"SansSerif.plain","style":0,"size":10},"noBreak":false,"color":{"argb":"ff000000"},"placement":"FREE","horizontalPlacement":"FREE","verticalPlacement":"FREE","showLabel":true,"shape":null,"layoutText":null}],"allPortLabels":[],"mainLabel":284},"thickness":-1.0,"color":{"argb":"ff000000"},"paths":[],"reference":null},{"@id":285,"ports":[162,77],"labelManager":{"innerLabels":[{"type":"text","@id":286,"inputText":"db804694002d5630","font":{"fontName":"SansSerif.plain","style":0,"size":10},"noBreak":false,"color":{"argb":"ff000000"},"placement":"FREE","horizontalPlacement":"FREE","verticalPlacement":"FREE","showLabel":true,"shape":null,"layoutText":null}],"allPortLabels":[],"mainLabel":286},"thickness":-1.0,"color":{"argb":"ff000000"},"paths":[],"reference":null},{"@id":287,"ports":[128,210],"labelManager":{"innerLabels":[{"type":"text","@id":288,"inputText":"e489350e13a91bbc","font":{"fontName":"SansSerif.plain","style":0,"size":10},"noBreak":false,"color":{"argb":"ff000000"},"placement":"FREE","horizontalPlacement":"FREE","verticalPlacement":"FREE","showLabel":true,"shape":null,"layoutText":null}],"allPortLabels":[],"mainLabel":288},"thickness":-1.0,"color":{"argb":"ff000000"},"paths":[],"reference":null},{"@id":289,"ports":[182,186],"labelManager":{"innerLabels":[{"type":"text","@id":290,"inputText":"703656e03afb4608","font":{"fontName":"SansSerif.plain","style":0,"size":10},"noBreak":false,"color":{"argb":"ff000000"},"placement":"FREE","horizontalPlacement":"FREE","verticalPlacement":"FREE","showLabel":true,"shape":null,"layoutText":null}],"allPortLabels":[],"mainLabel":290},"thickness":-1.0,"color":{"argb":"ff000000"},"paths":[],"reference":null},{"@id":291,"ports":[246,154],"labelManager":{"innerLabels":[{"type":"text","@id":292,"inputText":"2136910a8fd22a90","font":{"fontName":"SansSerif.plain","style":0,"size":10},"noBreak":false,"color":{"argb":"ff000000"},"placement":"FREE","horizontalPlacement":"FREE","verticalPlacement":"FREE","showLabel":true,"shape":null,"layoutText":null}],"allPortLabels":[],"mainLabel":292},"thickness":-1.0,"color":{"argb":"ff000000"},"paths":[],"reference":null},{"@id":293,"ports":[174,240],"labelManager":{"innerLabels":[{"type":"text","@id":294,"inputText":"404ae9762b13bede","font":{"fontName":"SansSerif.plain","style":0,"size":10},"noBreak":false,"color":{"argb":"ff000000"},"placement":"FREE","horizontalPlacement":"FREE","verticalPlacement":"FREE","showLabel":true,"shape":null,"layoutText":null}],"allPortLabels":[],"mainLabel":294},"thickness":-1.0,"color":{"argb":"ff000000"},"paths":[],"reference":null},{"@id":295,"ports":[77,222],"labelManager":{"innerLabels":[{"type":"text","@id":296,"inputText":"11a493801f5ef22f","font":{"fontName":"SansSerif.plain","style":0,"size":10},"noBreak":false,"color":{"argb":"ff000000"},"placement":"FREE","horizontalPlacement":"FREE","verticalPlacement":"FREE","showLabel":true,"shape":null,"layoutText":null}],"allPortLabels":[],"mainLabel":296},"thickness":-1.0,"color":{"argb":"ff000000"},"paths":[],"reference":null},{"@id":297,"ports":[222,210],"labelManager":{"innerLabels":[{"type":"text","@id":298,"inputText":"eafb315636122bcd","font":{"fontName":"SansSerif.plain","style":0,"size":10},"noBreak":false,"color":{"argb":"ff000000"},"placement":"FREE","horizontalPlacement":"FREE","verticalPlacement":"FREE","showLabel":true,"shape":null,"layoutText":null}],"allPortLabels":[],"mainLabel":298},"thickness":-1.0,"color":{"argb":"ff000000"},"paths":[],"reference":null},{"@id":299,"ports":[190,186],"labelManager":{"innerLabels":[{"type":"text","@id":300,"inputText":"c129f36894ab86a1","font":{"fontName":"SansSerif.plain","style":0,"size":10},"noBreak":false,"color":{"argb":"ff000000"},"placement":"FREE","horizontalPlacement":"FREE","verticalPlacement":"FREE","showLabel":true,"shape":null,"layoutText":null}],"allPortLabels":[],"mainLabel":300},"thickness":-1.0,"color":{"argb":"ff000000"},"paths":[],"reference":null},{"@id":301,"ports":[246,124],"labelManager":{"innerLabels":[{"type":"text","@id":302,"inputText":"1279c7b02a245b79","font":{"fontName":"SansSerif.plain","style":0,"size":10},"noBreak":false,"color":{"argb":"ff000000"},"placement":"FREE","horizontalPlacement":"FREE","verticalPlacement":"FREE","showLabel":true,"shape":null,"layoutText":null}],"allPortLabels":[],"mainLabel":302},"thickness":-1.0,"color":{"argb":"ff000000"},"paths":[],"reference":null},{"@id":303,"ports":[222,190],"labelManager":{"innerLabels":[{"type":"text","@id":304,"inputText":"337f3e9b535e32d2","font":{"fontName":"SansSerif.plain","style":0,"size":10},"noBreak":false,"color":{"argb":"ff000000"},"placement":"FREE","horizontalPlacement":"FREE","verticalPlacement":"FREE","showLabel":true,"shape":null,"layoutText":null}],"allPortLabels":[],"mainLabel":304},"thickness":-1.0,"color":{"argb":"ff000000"},"paths":[],"reference":null},{"@id":305,"ports":[158,124],"labelManager":{"innerLabels":[{"type":"text","@id":306,"inputText":"6b3e67252511ee5f","font":{"fontName":"SansSerif.plain","style":0,"size":10},"noBreak":false,"color":{"argb":"ff000000"},"placement":"FREE","horizontalPlacement":"FREE","verticalPlacement":"FREE","showLabel":true,"shape":null,"layoutText":null}],"allPortLabels":[],"mainLabel":306},"thickness":-1.0,"color":{"argb":"ff000000"},"paths":[],"reference":null},{"@id":307,"ports":[210,32],"labelManager":{"innerLabels":[{"type":"text","@id":308,"inputText":"2aa04701dc91a2c7","font":{"fontName":"SansSerif.plain","style":0,"size":10},"noBreak":false,"color":{"argb":"ff000000"},"placement":"FREE","horizontalPlacement":"FREE","verticalPlacement":"FREE","showLabel":true,"shape":null,"layoutText":null}],"allPortLabels":[],"mainLabel":308},"thickness":-1.0,"color":{"argb":"ff000000"},"paths":[],"reference":null},{"@id":309,"ports":[195,217],"labelManager":{"innerLabels":[{"type":"text","@id":310,"inputText":"bf97fa328c61b7af","font":{"fontName":"SansSerif.plain","style":0,"size":10},"noBreak":false,"color":{"argb":"ff000000"},"placement":"FREE","horizontalPlacement":"FREE","verticalPlacement":"FREE","showLabel":true,"shape":null,"layoutText":null}],"allPortLabels":[],"mainLabel":310},"thickness":-1.0,"color":{"argb":"ff000000"},"paths":[],"reference":null},{"@id":311,"ports":[37,240],"labelManager":{"innerLabels":[{"type":"text","@id":312,"inputText":"a74b7183134bd0a1","font":{"fontName":"SansSerif.plain","style":0,"size":10},"noBreak":false,"color":{"argb":"ff000000"},"placement":"FREE","horizontalPlacement":"FREE","verticalPlacement":"FREE","showLabel":true,"shape":null,"layoutText":null}],"allPortLabels":[],"mainLabel":312},"thickness":-1.0,"color":{"argb":"ff000000"},"paths":[],"reference":null},{"@id":313,"ports":[73,246],"labelManager":{"innerLabels":[{"type":"text","@id":314,"inputText":"9e2564c9125d5c08","font":{"fontName":"SansSerif.plain","style":0,"size":10},"noBreak":false,"color":{"argb":"ff000000"},"placement":"FREE","horizontalPlacement":"FREE","verticalPlacement":"FREE","showLabel":true,"shape":null,"layoutText":null}],"allPortLabels":[],"mainLabel":314},"thickness":-1.0,"color":{"argb":"ff000000"},"paths":[],"reference":null},{"@id":315,"ports":[71,150,88],"labelManager":{"innerLabels":[{"type":"text","@id":316,"inputText":"f8daab67a7db8bd0","font":{"fontName":"SansSerif.plain","style":0,"size":10},"noBreak":false,"color":{"argb":"ff000000"},"placement":"FREE","horizontalPlacement":"FREE","verticalPlacement":"FREE","showLabel":true,"shape":null,"layoutText":null}],"allPortLabels":[],"mainLabel":316},"thickness":-1.0,"color":{"argb":"ff000000"},"paths":[],"reference":null},{"@id":317,"ports":[242,69,244],"labelManager":{"innerLabels":[{"type":"text","@id":318,"inputText":"c20243e0a9cd0aaa","font":{"fontName":"SansSerif.plain","style":0,"size":10},"noBreak":false,"color":{"argb":"ff000000"},"placement":"FREE","horizontalPlacement":"FREE","verticalPlacement":"FREE","showLabel":true,"shape":null,"layoutText":null}],"allPortLabels":[],"mainLabel":318},"thickness":-1.0,"color":{"argb":"ff000000"},"paths":[],"reference":null}],"edgeBundles":[]}